MANIFEST.in
setup.py
.idea/kscan_pocs.iml
.idea/misc.xml
.idea/modules.xml
.idea/vcs.xml
.idea/workspace.xml
.idea/inspectionProfiles/profiles_settings.xml
kscanPoc.egg-info/PKG-INFO
kscanPoc.egg-info/SOURCES.txt
kscanPoc.egg-info/dependency_links.txt
kscanPoc.egg-info/requires.txt
kscanPoc.egg-info/top_level.txt
kscanPoc.egg-info/zip-safe
kscanpocs/AmbariCheck.py
kscanpocs/ApolloCheck.py
kscanpocs/ArangoDBCheck.py
kscanpocs/CelloCheck.py
kscanpocs/DockerRegistryCheck.py
kscanpocs/EsUnauthCheck.py
kscanpocs/HTTPBasicAuthCheck.py
kscanpocs/HarborCheck.py
kscanpocs/IscsiCheck.py
kscanpocs/KialiCheck.py
kscanpocs/NexusCheck.py
kscanpocs/NfsCheck.py
kscanpocs/OpenStackCheck.py
kscanpocs/OracleCheck.py
kscanpocs/RsyncCheck.py
kscanpocs/SentinelCheck.py
kscanpocs/ShipyardCheck.py
kscanpocs/SshPasswdCheck.py
kscanpocs/TelnetCheck.py
kscanpocs/__init__.py
kscanpocs/ftpCheck.py
kscanpocs/grafanaCheck.py
kscanpocs/hueCheck.py
kscanpocs/jenkinsCheck.py
kscanpocs/k8sCheck.py
kscanpocs/memcachedCheck.py
kscanpocs/mongodbCheck.py
kscanpocs/mysqlCheck.py
kscanpocs/postgresqlCheck.py
kscanpocs/rabbitMQCheck.py
kscanpocs/rancherCheck.py
kscanpocs/rangerCheck.py
kscanpocs/redisCheck.py
kscanpocs/sshCheck.py
kscanpocs/supersetCheck.py
kscanpocs/swarmCheck.py
kscanpocs/yarnCheck.py
kscanpocs/zabbixCheck.py
kscanpocs/zookeeperCheck.py
kscanpocs/lib/__init__.py
kscanpocs/lib/core/__init__.py
kscanpocs/lib/core/nmapwrapper.py
kscanpocs/lib/core/settings.py
kscanpocs/lib/thirdparty/Host.py
kscanpocs/lib/thirdparty/Parser.py
kscanpocs/lib/thirdparty/Service.py
kscanpocs/lib/thirdparty/Session.py
kscanpocs/lib/thirdparty/__init__.py
kscanpocs/utils/__init__.py
kscanpocs/utils/getFile.py
kscanpocs/var/__init__.py
kscanpocs/var/ftp_passwd.txt
kscanpocs/var/ftp_user.txt
kscanpocs/var/mongodb_passwd.txt
kscanpocs/var/mongodb_user.txt
kscanpocs/var/mysql_passwd.txt
kscanpocs/var/mysql_user.txt
kscanpocs/var/ssh_passwd.txt
kscanpocs/var/ssh_user.txt
kscanpocs/var/tomcat_passwd.txt
kscanpocs/var/tomcat_user.txt
kscanpocs/var/top200passwd.txt