Metadata-Version: 1.2
Name: kscanPoc
Version: 0.0.3
Summary: kscan kscanpocs
Home-page: UNKNOWN
Author: wanqian1
Author-email: wanqian1@kingsoft.com
Maintainer: chenyang7
Maintainer-email: chengyang7@kingsoft.com
License: UNKNOWN
Platform: UNKNOWN
